odoo/addons/account_invoice_import_invoice2data/README.rst
odoo/addons/account_invoice_import_invoice2data/__init__.py
odoo/addons/account_invoice_import_invoice2data/__manifest__.py
odoo/addons/account_invoice_import_invoice2data/demo/demo_data.xml
odoo/addons/account_invoice_import_invoice2data/i18n/account_invoice_import_invoice2data.pot
odoo/addons/account_invoice_import_invoice2data/i18n/de.po
odoo/addons/account_invoice_import_invoice2data/i18n/es.po
odoo/addons/account_invoice_import_invoice2data/i18n/nl.po
odoo/addons/account_invoice_import_invoice2data/i18n/pt.po
odoo/addons/account_invoice_import_invoice2data/i18n/sl.po
odoo/addons/account_invoice_import_invoice2data/readme/CONFIGURE.rst
odoo/addons/account_invoice_import_invoice2data/readme/CONTRIBUTORS.rst
odoo/addons/account_invoice_import_invoice2data/readme/DESCRIPTION.rst
odoo/addons/account_invoice_import_invoice2data/readme/INSTALL.rst
odoo/addons/account_invoice_import_invoice2data/static/description/icon.png
odoo/addons/account_invoice_import_invoice2data/static/description/index.html
odoo/addons/account_invoice_import_invoice2data/tests/__init__.py
odoo/addons/account_invoice_import_invoice2data/tests/test_invoice_import.py
odoo/addons/account_invoice_import_invoice2data/tests/pdf/invoice_free_fiber_201507.pdf
odoo/addons/account_invoice_import_invoice2data/wizard/__init__.py
odoo/addons/account_invoice_import_invoice2data/wizard/account_invoice_import.py
odoo/addons/account_invoice_import_invoice2data/wizard/account_invoice_import_view.xml
odoo12_addon_account_invoice_import_invoice2data-12.0.1.1.1.dist-info/METADATA
odoo12_addon_account_invoice_import_invoice2data-12.0.1.1.1.dist-info/WHEEL
odoo12_addon_account_invoice_import_invoice2data-12.0.1.1.1.dist-info/top_level.txt
odoo12_addon_account_invoice_import_invoice2data-12.0.1.1.1.dist-info/RECORD
