Metadata-Version: 2.1
Name: odoo12-addon-account-invoice-import-invoice2data
Version: 12.0.1.1.1
Summary: Import supplier invoices using the invoice2data lib
Home-page: https://github.com/OCA/edi
Author: Akretion,Odoo Community Association (OCA)
Author-email: support@odoo-community.org
License: AGPL-3
Platform: UNKNOWN
Classifier: Programming Language :: Python
Classifier: Framework :: Odoo
Classifier: Framework :: Odoo :: 12.0
Classifier: License :: OSI Approved :: GNU Affero General Public License v3
Requires-Python: >=3.5
Requires-Dist: invoice2data
Requires-Dist: odoo12-addon-account-invoice-import
Requires-Dist: odoo <12.1dev,>=12.0a
